nextinspace/__init__.py
nextinspace/__main__.py
nextinspace/cli/__init__.py
nextinspace/cli/console.py
nextinspace/cli/parser.py
nextinspace/cli/viewer.py
nextinspace-3.0.1.dist-info/LICENSE
nextinspace-3.0.1.dist-info/METADATA
nextinspace-3.0.1.dist-info/WHEEL
nextinspace-3.0.1.dist-info/entry_points.txt
nextinspace-3.0.1.dist-info/RECORD
