Metadata-Version: 2.1
Name: nextinspace
Version: 3.0.1
Summary: Never miss a launch.
Home-page: https://github.com/gideonshaked/nextinspace
License: GPL-3.0-or-later
Keywords: space,nextinspace,space news,spaceflight,rockets
Author: Gideon Shaked
Author-email: gideonshaked@gmail.com
Maintainer: Gideon Shaked
Maintainer-email: gideonshaked@gmail.com
Requires-Python: >=3.10,<4.0
Classifier: Environment :: Console
Classifier: License :: OSI Approved :: GNU General Public License (GPL)
Classifier: License :: OSI Approved :: GNU General Public License v3 (GPLv3)
Classifier: License :: OSI Approved :: GNU General Public License v3 or later (GPLv3+)
Classifier: Natural Language :: English
Classifier: Programming Language :: Python
Classifier: Programming Language :: Python :: 3
Classifier: Programming Language :: Python :: 3.10
Classifier: Programming Language :: Python :: 3.11
Classifier: Programming Language :: Python :: 3.12
Classifier: Programming Language :: Python :: 3.13
Classifier: Programming Language :: Python :: 3 :: Only
Requires-Dist: colorama (>=0.4.3,<0.5.0)
Requires-Dist: requests (>=2.24,<3.0)
Project-URL: Repository, https://github.com/gideonshaked/nextinspace
